[
  {
    "course": "EDIFICACOES SUBSEQUENTE",
    "semester": 1,
    "weekday": "segunda",
    "start": "18:20",
    "end": "19:10",
    "className": "INGLES TECNICO",
    "teacher": [
      {
        "name": "RAMON BRASILEI",
        "link": "https://joaopessoa.ifpb.edu.br/horario/professor/801"
      }
    ],
    "location": [
      {
        "name": "SALA 06",
        "link": "https://joaopessoa.ifpb.edu.br/horario/sala/98"
      }
    ]
  },
  {
    "course": "EDIFICACOES SUBSEQUENTE",
    "semester": 1,
    "weekday": "terca",
    "start": "18:20",
    "end": "19:10",
    "className": "DES TECNICO I",
    "teacher": [
      {
        "name": "VERA REGINA",
        "link": "https://joaopessoa.ifpb.edu.br/horario/professor/412"
      },
      {
        "name": "EUGENIO NETO",
        "link": "https://joaopessoa.ifpb.edu.br/horario/professor/122"
      }
    ],
    "location": [
      {
        "name": "SDES. 01",
        "link": "https://joaopessoa.ifpb.edu.br/horario/sala/46"
      },
      {
        "name": "SDES. 02",
        "link": "https://joaopessoa.ifpb.edu.br/horario/sala/45"
      }
    ]
  },
  {
    "course": "EDIFICACOES SUBSEQUENTE",
    "semester": 1,
    "weekday": "quarta",
    "start": "18:20",
    "end": "19:10",
    "className": "QUIMICA APLIC",
    "teacher": [
      {
        "name": "ARQUIMEDES",
        "link": "https://joaopessoa.ifpb.edu.br/horario/professor/799"
      }
    ],
    "location": [
      {
        "name": "SALA 06",
        "link": "https://joaopessoa.ifpb.edu.br/horario/sala/98"
      }
    ]
  },
  {
    "course": "EDIFICACOES SUBSEQUENTE",
    "semester": 1,
    "weekday": "quinta",
    "start": "18:20",
    "end": "19:10",
    "className": "MAT APLIC",
    "teacher": [
      {
        "name": "DIEGO AYLLO",
        "link": "https://joaopessoa.ifpb.edu.br/horario/professor/68"
      }
    ],
    "location": [
      {
        "name": "SALA 06",
        "link": "https://joaopessoa.ifpb.edu.br/horario/sala/98"
      }
    ]
  },
  {
    "course": "EDIFICACOES SUBSEQUENTE",
    "semester": 1,
    "weekday": "sexta",
    "start": "18:20",
    "end": "19:10",
    "className": "PSIC TRABALHO",
    "teacher": [
      {
        "name": "RENNATA",
        "link": "https://joaopessoa.ifpb.edu.br/horario/professor/794"
      }
    ],
    "location": [
      {
        "name": "SALA 06",
        "link": "https://joaopessoa.ifpb.edu.br/horario/sala/98"
      }
    ]
  },
  {
    "course": "EDIFICACOES SUBSEQUENTE",
    "semester": 1,
    "weekday": "segunda",
    "start": "19:10",
    "end": "20:00",
    "className": "INGLES TECNICO",
    "teacher": [
      {
        "name": "RAMON BRASILEI",
        "link": "https://joaopessoa.ifpb.edu.br/horario/professor/801"
      }
    ],
    "location": [
      {
        "name": "SALA 06",
        "link": "https://joaopessoa.ifpb.edu.br/horario/sala/98"
      }
    ]
  },
  {
    "course": "EDIFICACOES SUBSEQUENTE",
    "semester": 1,
    "weekday": "terca",
    "start": "19:10",
    "end": "20:00",
    "className": "DES TECNICO I",
    "teacher": [
      {
        "name": "VERA REGINA",
        "link": "https://joaopessoa.ifpb.edu.br/horario/professor/412"
      },
      {
        "name": "EUGENIO NETO",
        "link": "https://joaopessoa.ifpb.edu.br/horario/professor/122"
      }
    ],
    "location": [
      {
        "name": "SDES. 01",
        "link": "https://joaopessoa.ifpb.edu.br/horario/sala/46"
      },
      {
        "name": "SDES. 02",
        "link": "https://joaopessoa.ifpb.edu.br/horario/sala/45"
      }
    ]
  },
  {
    "course": "EDIFICACOES SUBSEQUENTE",
    "semester": 1,
    "weekday": "quarta",
    "start": "19:10",
    "end": "20:00",
    "className": "QUIMICA APLIC",
    "teacher": [
      {
        "name": "ARQUIMEDES",
        "link": "https://joaopessoa.ifpb.edu.br/horario/professor/799"
      }
    ],
    "location": [
      {
        "name": "SALA 06",
        "link": "https://joaopessoa.ifpb.edu.br/horario/sala/98"
      }
    ]
  },
  {
    "course": "EDIFICACOES SUBSEQUENTE",
    "semester": 1,
    "weekday": "quinta",
    "start": "19:10",
    "end": "20:00",
    "className": "INFOR BASICA",
    "teacher": [
      {
        "name": "SILVIO LUCAS",
        "link": "https://joaopessoa.ifpb.edu.br/horario/professor/267"
      }
    ],
    "location": [
      {
        "name": "SL INFO 18",
        "link": "https://joaopessoa.ifpb.edu.br/horario/sala/83"
      }
    ]
  },
  {
    "course": "EDIFICACOES SUBSEQUENTE",
    "semester": 1,
    "weekday": "sexta",
    "start": "19:10",
    "end": "20:00",
    "className": "PSIC TRABALHO",
    "teacher": [
      {
        "name": "RENNATA",
        "link": "https://joaopessoa.ifpb.edu.br/horario/professor/794"
      }
    ],
    "location": [
      {
        "name": "SALA 06",
        "link": "https://joaopessoa.ifpb.edu.br/horario/sala/98"
      }
    ]
  },
  {
    "course": "EDIFICACOES SUBSEQUENTE",
    "semester": 1,
    "weekday": "segunda",
    "start": "20:00",
    "end": "20:50",
    "className": "FISICA APLIC",
    "teacher": [
      {
        "name": "JOSE GILBERTO",
        "link": "https://joaopessoa.ifpb.edu.br/horario/professor/220"
      }
    ],
    "location": [
      {
        "name": "SALA 06",
        "link": "https://joaopessoa.ifpb.edu.br/horario/sala/98"
      }
    ]
  },
  {
    "course": "EDIFICACOES SUBSEQUENTE",
    "semester": 1,
    "weekday": "terca",
    "start": "20:00",
    "end": "20:50",
    "className": "DES TECNICO I",
    "teacher": [
      {
        "name": "VERA REGINA",
        "link": "https://joaopessoa.ifpb.edu.br/horario/professor/412"
      },
      {
        "name": "EUGENIO NETO",
        "link": "https://joaopessoa.ifpb.edu.br/horario/professor/122"
      }
    ],
    "location": [
      {
        "name": "SDES. 01",
        "link": "https://joaopessoa.ifpb.edu.br/horario/sala/46"
      },
      {
        "name": "SDES. 02",
        "link": "https://joaopessoa.ifpb.edu.br/horario/sala/45"
      }
    ]
  },
  {
    "course": "EDIFICACOES SUBSEQUENTE",
    "semester": 1,
    "weekday": "quarta",
    "start": "20:00",
    "end": "20:50",
    "className": "MAT APLIC",
    "teacher": [
      {
        "name": "DIEGO AYLLO",
        "link": "https://joaopessoa.ifpb.edu.br/horario/professor/68"
      }
    ],
    "location": [
      {
        "name": "SALA 06",
        "link": "https://joaopessoa.ifpb.edu.br/horario/sala/98"
      }
    ]
  },
  {
    "course": "EDIFICACOES SUBSEQUENTE",
    "semester": 1,
    "weekday": "quinta",
    "start": "20:00",
    "end": "20:50",
    "className": "INFOR BASICA",
    "teacher": [
      {
        "name": "SILVIO LUCAS",
        "link": "https://joaopessoa.ifpb.edu.br/horario/professor/267"
      }
    ],
    "location": [
      {
        "name": "SL INFO 18",
        "link": "https://joaopessoa.ifpb.edu.br/horario/sala/83"
      }
    ]
  },
  {
    "course": "EDIFICACOES SUBSEQUENTE",
    "semester": 1,
    "weekday": "sexta",
    "start": "20:00",
    "end": "20:50",
    "className": "LING PORT",
    "teacher": [
      {
        "name": "JOÃO EDSON",
        "link": "https://joaopessoa.ifpb.edu.br/horario/professor/831"
      }
    ],
    "location": [
      {
        "name": "SALA 06",
        "link": "https://joaopessoa.ifpb.edu.br/horario/sala/98"
      }
    ]
  },
  {
    "course": "EDIFICACOES SUBSEQUENTE",
    "semester": 1,
    "weekday": "segunda",
    "start": "20:50",
    "end": "21:40",
    "className": "FISICA APLIC",
    "teacher": [
      {
        "name": "JOSE GILBERTO",
        "link": "https://joaopessoa.ifpb.edu.br/horario/professor/220"
      }
    ],
    "location": [
      {
        "name": "SALA 06",
        "link": "https://joaopessoa.ifpb.edu.br/horario/sala/98"
      }
    ]
  },
  {
    "course": "EDIFICACOES SUBSEQUENTE",
    "semester": 1,
    "weekday": "terca",
    "start": "20:50",
    "end": "21:40",
    "className": "DES TECNICO I",
    "teacher": [
      {
        "name": "VERA REGINA",
        "link": "https://joaopessoa.ifpb.edu.br/horario/professor/412"
      },
      {
        "name": "EUGENIO NETO",
        "link": "https://joaopessoa.ifpb.edu.br/horario/professor/122"
      }
    ],
    "location": [
      {
        "name": "SDES. 01",
        "link": "https://joaopessoa.ifpb.edu.br/horario/sala/46"
      },
      {
        "name": "SDES. 02",
        "link": "https://joaopessoa.ifpb.edu.br/horario/sala/45"
      }
    ]
  },
  {
    "course": "EDIFICACOES SUBSEQUENTE",
    "semester": 1,
    "weekday": "quarta",
    "start": "20:50",
    "end": "21:40",
    "className": "MAT APLIC",
    "teacher": [
      {
        "name": "DIEGO AYLLO",
        "link": "https://joaopessoa.ifpb.edu.br/horario/professor/68"
      }
    ],
    "location": [
      {
        "name": "SALA 06",
        "link": "https://joaopessoa.ifpb.edu.br/horario/sala/98"
      }
    ]
  },
  {
    "course": "EDIFICACOES SUBSEQUENTE",
    "semester": 1,
    "weekday": "quinta",
    "start": "20:50",
    "end": "21:40",
    "className": "INFOR BASICA",
    "teacher": [
      {
        "name": "SILVIO LUCAS",
        "link": "https://joaopessoa.ifpb.edu.br/horario/professor/267"
      }
    ],
    "location": [
      {
        "name": "SL INFO 18",
        "link": "https://joaopessoa.ifpb.edu.br/horario/sala/83"
      }
    ]
  },
  {
    "course": "EDIFICACOES SUBSEQUENTE",
    "semester": 1,
    "weekday": "sexta",
    "start": "20:50",
    "end": "21:40",
    "className": "LING PORT",
    "teacher": [
      {
        "name": "JOÃO EDSON",
        "link": "https://joaopessoa.ifpb.edu.br/horario/professor/831"
      }
    ],
    "location": [
      {
        "name": "SALA 06",
        "link": "https://joaopessoa.ifpb.edu.br/horario/sala/98"
      }
    ]
  },
  {
    "course": "EDIFICACOES SUBSEQUENTE",
    "semester": 2,
    "weekday": "segunda",
    "start": "18:20",
    "end": "19:10",
    "className": "TEC QUALIDADE",
    "teacher": [
      {
        "name": "ALEXSANDRA",
        "link": "https://joaopessoa.ifpb.edu.br/horario/professor/18"
      }
    ],
    "location": [
      {
        "name": "SALA 05",
        "link": "https://joaopessoa.ifpb.edu.br/horario/sala/99"
      }
    ]
  },
  {
    "course": "EDIFICACOES SUBSEQUENTE",
    "semester": 2,
    "weekday": "terca",
    "start": "18:20",
    "end": "19:10",
    "className": "MAT CON CIV I",
    "teacher": [
      {
        "name": "VAMBERTO",
        "link": "https://joaopessoa.ifpb.edu.br/horario/professor/410"
      }
    ],
    "location": [
      {
        "name": "LAB MAT.1",
        "link": "https://joaopessoa.ifpb.edu.br/horario/laboratorio/62"
      }
    ]
  },
  {
    "course": "EDIFICACOES SUBSEQUENTE",
    "semester": 2,
    "weekday": "quarta",
    "start": "18:20",
    "end": "19:10",
    "className": "DES TECNICO II",
    "teacher": [
      {
        "name": "VERA REGINA",
        "link": "https://joaopessoa.ifpb.edu.br/horario/professor/412"
      }
    ],
    "location": [
      {
        "name": "SDES. 01",
        "link": "https://joaopessoa.ifpb.edu.br/horario/sala/46"
      }
    ]
  },
  {
    "course": "EDIFICACOES SUBSEQUENTE",
    "semester": 2,
    "weekday": "quinta",
    "start": "18:20",
    "end": "19:10",
    "className": "DES AUX COM I",
    "teacher": [
      {
        "name": "RENATA PAIVA",
        "link": "https://joaopessoa.ifpb.edu.br/horario/professor/9"
      }
    ],
    "location": [
      {
        "name": "SL INFO 31",
        "link": "https://joaopessoa.ifpb.edu.br/horario/sala/54"
      }
    ]
  },
  {
    "course": "EDIFICACOES SUBSEQUENTE",
    "semester": 2,
    "weekday": "sexta",
    "start": "18:20",
    "end": "19:10",
    "className": "ESTAB CONCRETO",
    "teacher": [
      {
        "name": "GINETOM ARAUJO",
        "link": "https://joaopessoa.ifpb.edu.br/horario/professor/441"
      }
    ],
    "location": [
      {
        "name": "SALA 05",
        "link": "https://joaopessoa.ifpb.edu.br/horario/sala/99"
      }
    ]
  },
  {
    "course": "EDIFICACOES SUBSEQUENTE",
    "semester": 2,
    "weekday": "segunda",
    "start": "19:10",
    "end": "20:00",
    "className": "TEC QUALIDADE",
    "teacher": [
      {
        "name": "ALEXSANDRA",
        "link": "https://joaopessoa.ifpb.edu.br/horario/professor/18"
      }
    ],
    "location": [
      {
        "name": "SALA 05",
        "link": "https://joaopessoa.ifpb.edu.br/horario/sala/99"
      }
    ]
  },
  {
    "course": "EDIFICACOES SUBSEQUENTE",
    "semester": 2,
    "weekday": "terca",
    "start": "19:10",
    "end": "20:00",
    "className": "MAT CON CIV I",
    "teacher": [
      {
        "name": "VAMBERTO",
        "link": "https://joaopessoa.ifpb.edu.br/horario/professor/410"
      }
    ],
    "location": [
      {
        "name": "LAB MAT.1",
        "link": "https://joaopessoa.ifpb.edu.br/horario/laboratorio/62"
      }
    ]
  },
  {
    "course": "EDIFICACOES SUBSEQUENTE",
    "semester": 2,
    "weekday": "quarta",
    "start": "19:10",
    "end": "20:00",
    "className": "DES TECNICO II",
    "teacher": [
      {
        "name": "VERA REGINA",
        "link": "https://joaopessoa.ifpb.edu.br/horario/professor/412"
      }
    ],
    "location": [
      {
        "name": "SDES. 01",
        "link": "https://joaopessoa.ifpb.edu.br/horario/sala/46"
      }
    ]
  },
  {
    "course": "EDIFICACOES SUBSEQUENTE",
    "semester": 2,
    "weekday": "quinta",
    "start": "19:10",
    "end": "20:00",
    "className": "DES AUX COM I",
    "teacher": [
      {
        "name": "RENATA PAIVA",
        "link": "https://joaopessoa.ifpb.edu.br/horario/professor/9"
      }
    ],
    "location": [
      {
        "name": "SL INFO 31",
        "link": "https://joaopessoa.ifpb.edu.br/horario/sala/54"
      }
    ]
  },
  {
    "course": "EDIFICACOES SUBSEQUENTE",
    "semester": 2,
    "weekday": "sexta",
    "start": "19:10",
    "end": "20:00",
    "className": "ESTAB CONCRETO",
    "teacher": [
      {
        "name": "GINETOM ARAUJO",
        "link": "https://joaopessoa.ifpb.edu.br/horario/professor/441"
      }
    ],
    "location": [
      {
        "name": "SALA 05",
        "link": "https://joaopessoa.ifpb.edu.br/horario/sala/99"
      }
    ]
  },
  {
    "course": "EDIFICACOES SUBSEQUENTE",
    "semester": 2,
    "weekday": "segunda",
    "start": "20:00",
    "end": "20:50",
    "className": "DES TECNICO II",
    "teacher": [
      {
        "name": "VERA REGINA",
        "link": "https://joaopessoa.ifpb.edu.br/horario/professor/412"
      }
    ],
    "location": [
      {
        "name": "SDES. 02",
        "link": "https://joaopessoa.ifpb.edu.br/horario/sala/45"
      }
    ]
  },
  {
    "course": "EDIFICACOES SUBSEQUENTE",
    "semester": 2,
    "weekday": "terca",
    "start": "20:00",
    "end": "20:50",
    "className": "HST",
    "teacher": [
      {
        "name": "EVANDRO",
        "link": "https://joaopessoa.ifpb.edu.br/horario/professor/126"
      }
    ],
    "location": [
      {
        "name": "SALA 05",
        "link": "https://joaopessoa.ifpb.edu.br/horario/sala/99"
      }
    ]
  },
  {
    "course": "EDIFICACOES SUBSEQUENTE",
    "semester": 2,
    "weekday": "quarta",
    "start": "20:00",
    "end": "20:50",
    "className": "DES TECNICO II",
    "teacher": [
      {
        "name": "VERA REGINA",
        "link": "https://joaopessoa.ifpb.edu.br/horario/professor/412"
      }
    ],
    "location": [
      {
        "name": "SDES. 01",
        "link": "https://joaopessoa.ifpb.edu.br/horario/sala/46"
      }
    ]
  },
  {
    "course": "EDIFICACOES SUBSEQUENTE",
    "semester": 2,
    "weekday": "quinta",
    "start": "20:00",
    "end": "20:50",
    "className": "DES AUX COM I",
    "teacher": [
      {
        "name": "RENATA PAIVA",
        "link": "https://joaopessoa.ifpb.edu.br/horario/professor/9"
      }
    ],
    "location": [
      {
        "name": "SL INFO 31",
        "link": "https://joaopessoa.ifpb.edu.br/horario/sala/54"
      }
    ]
  },
  {
    "course": "EDIFICACOES SUBSEQUENTE",
    "semester": 2,
    "weekday": "sexta",
    "start": "20:00",
    "end": "20:50",
    "className": "ESTAB CONCRETO",
    "teacher": [
      {
        "name": "GINETOM ARAUJO",
        "link": "https://joaopessoa.ifpb.edu.br/horario/professor/441"
      }
    ],
    "location": [
      {
        "name": "SALA 05",
        "link": "https://joaopessoa.ifpb.edu.br/horario/sala/99"
      }
    ]
  },
  {
    "course": "EDIFICACOES SUBSEQUENTE",
    "semester": 2,
    "weekday": "segunda",
    "start": "20:50",
    "end": "21:40",
    "className": "DES TECNICO II",
    "teacher": [
      {
        "name": "VERA REGINA",
        "link": "https://joaopessoa.ifpb.edu.br/horario/professor/412"
      }
    ],
    "location": [
      {
        "name": "SDES. 02",
        "link": "https://joaopessoa.ifpb.edu.br/horario/sala/45"
      }
    ]
  },
  {
    "course": "EDIFICACOES SUBSEQUENTE",
    "semester": 2,
    "weekday": "terca",
    "start": "20:50",
    "end": "21:40",
    "className": "HST",
    "teacher": [
      {
        "name": "EVANDRO",
        "link": "https://joaopessoa.ifpb.edu.br/horario/professor/126"
      }
    ],
    "location": [
      {
        "name": "SALA 05",
        "link": "https://joaopessoa.ifpb.edu.br/horario/sala/99"
      }
    ]
  },
  {
    "course": "EDIFICACOES SUBSEQUENTE",
    "semester": 3,
    "weekday": "terca",
    "start": "18:20",
    "end": "19:10",
    "className": "MEC SOLOS",
    "teacher": [
      {
        "name": "EVANDRO",
        "link": "https://joaopessoa.ifpb.edu.br/horario/professor/126"
      }
    ],
    "location": [
      {
        "name": "LAB SOLOS",
        "link": "https://joaopessoa.ifpb.edu.br/horario/laboratorio/64"
      }
    ]
  },
  {
    "course": "EDIFICACOES SUBSEQUENTE",
    "semester": 3,
    "weekday": "quarta",
    "start": "18:20",
    "end": "19:10",
    "className": "TEC CONST A",
    "teacher": [
      {
        "name": "RENATA PAIVA",
        "link": "https://joaopessoa.ifpb.edu.br/horario/professor/9"
      }
    ],
    "location": [
      {
        "name": "SALA 39",
        "link": "https://joaopessoa.ifpb.edu.br/horario/sala/42"
      }
    ]
  },
  {
    "course": "EDIFICACOES SUBSEQUENTE",
    "semester": 3,
    "weekday": "quinta",
    "start": "18:20",
    "end": "19:10",
    "className": "TOPOGRAFIA",
    "teacher": [
      {
        "name": "MARCONI ANTAO",
        "link": "https://joaopessoa.ifpb.edu.br/horario/professor/283"
      }
    ],
    "location": [
      {
        "name": "SALA 04",
        "link": "https://joaopessoa.ifpb.edu.br/horario/sala/100"
      }
    ]
  },
  {
    "course": "EDIFICACOES SUBSEQUENTE",
    "semester": 3,
    "weekday": "sexta",
    "start": "18:20",
    "end": "19:10",
    "className": "TEC CONST A",
    "teacher": [
      {
        "name": "MELLYNE ",
        "link": "https://joaopessoa.ifpb.edu.br/horario/professor/796"
      }
    ],
    "location": [
      {
        "name": "SALA 04",
        "link": "https://joaopessoa.ifpb.edu.br/horario/sala/100"
      }
    ]
  },
  {
    "course": "EDIFICACOES SUBSEQUENTE",
    "semester": 3,
    "weekday": "segunda",
    "start": "19:10",
    "end": "20:00",
    "className": "MAT CON CIV II",
    "teacher": [
      {
        "name": "VAMBERTO",
        "link": "https://joaopessoa.ifpb.edu.br/horario/professor/410"
      }
    ],
    "location": [
      {
        "name": "LAB MAT.1",
        "link": "https://joaopessoa.ifpb.edu.br/horario/laboratorio/62"
      }
    ]
  },
  {
    "course": "EDIFICACOES SUBSEQUENTE",
    "semester": 3,
    "weekday": "terca",
    "start": "19:10",
    "end": "20:00",
    "className": "DES AUX COM II",
    "teacher": [
      {
        "name": "MANOEL BRITO",
        "link": "https://joaopessoa.ifpb.edu.br/horario/professor/266"
      }
    ],
    "location": [
      {
        "name": "SL INFO 31",
        "link": "https://joaopessoa.ifpb.edu.br/horario/sala/54"
      }
    ]
  },
  {
    "course": "EDIFICACOES SUBSEQUENTE",
    "semester": 3,
    "weekday": "quarta",
    "start": "19:10",
    "end": "20:00",
    "className": "TEC CONST A",
    "teacher": [
      {
        "name": "RENATA PAIVA",
        "link": "https://joaopessoa.ifpb.edu.br/horario/professor/9"
      }
    ],
    "location": [
      {
        "name": "SALA 39",
        "link": "https://joaopessoa.ifpb.edu.br/horario/sala/42"
      }
    ]
  },
  {
    "course": "EDIFICACOES SUBSEQUENTE",
    "semester": 3,
    "weekday": "quinta",
    "start": "19:10",
    "end": "20:00",
    "className": "TOPOGRAFIA",
    "teacher": [
      {
        "name": "MARCONI ANTAO",
        "link": "https://joaopessoa.ifpb.edu.br/horario/professor/283"
      }
    ],
    "location": [
      {
        "name": "SALA 04",
        "link": "https://joaopessoa.ifpb.edu.br/horario/sala/100"
      }
    ]
  },
  {
    "course": "EDIFICACOES SUBSEQUENTE",
    "semester": 3,
    "weekday": "sexta",
    "start": "19:10",
    "end": "20:00",
    "className": "TEC CONST A",
    "teacher": [
      {
        "name": "MELLYNE ",
        "link": "https://joaopessoa.ifpb.edu.br/horario/professor/796"
      }
    ],
    "location": [
      {
        "name": "SALA 04",
        "link": "https://joaopessoa.ifpb.edu.br/horario/sala/100"
      }
    ]
  },
  {
    "course": "EDIFICACOES SUBSEQUENTE",
    "semester": 3,
    "weekday": "segunda",
    "start": "20:00",
    "end": "20:50",
    "className": "MAT CON CIV II",
    "teacher": [
      {
        "name": "VAMBERTO",
        "link": "https://joaopessoa.ifpb.edu.br/horario/professor/410"
      }
    ],
    "location": [
      {
        "name": "LAB MAT.1",
        "link": "https://joaopessoa.ifpb.edu.br/horario/laboratorio/62"
      }
    ]
  },
  {
    "course": "EDIFICACOES SUBSEQUENTE",
    "semester": 3,
    "weekday": "terca",
    "start": "20:00",
    "end": "20:50",
    "className": "DES AUX COM II",
    "teacher": [
      {
        "name": "MANOEL BRITO",
        "link": "https://joaopessoa.ifpb.edu.br/horario/professor/266"
      }
    ],
    "location": [
      {
        "name": "SL INFO 31",
        "link": "https://joaopessoa.ifpb.edu.br/horario/sala/54"
      }
    ]
  },
  {
    "course": "EDIFICACOES SUBSEQUENTE",
    "semester": 3,
    "weekday": "quarta",
    "start": "20:00",
    "end": "20:50",
    "className": "TEC CONST A",
    "teacher": [
      {
        "name": "RENATA PAIVA",
        "link": "https://joaopessoa.ifpb.edu.br/horario/professor/9"
      }
    ],
    "location": [
      {
        "name": "SALA 39",
        "link": "https://joaopessoa.ifpb.edu.br/horario/sala/42"
      }
    ]
  },
  {
    "course": "EDIFICACOES SUBSEQUENTE",
    "semester": 3,
    "weekday": "quinta",
    "start": "20:00",
    "end": "20:50",
    "className": "MEC SOLOS",
    "teacher": [
      {
        "name": "EVANDRO",
        "link": "https://joaopessoa.ifpb.edu.br/horario/professor/126"
      }
    ],
    "location": [
      {
        "name": "LAB SOLOS",
        "link": "https://joaopessoa.ifpb.edu.br/horario/laboratorio/64"
      }
    ]
  },
  {
    "course": "EDIFICACOES SUBSEQUENTE",
    "semester": 3,
    "weekday": "sexta",
    "start": "20:00",
    "end": "20:50",
    "className": "TEC CONST A",
    "teacher": [
      {
        "name": "MELLYNE ",
        "link": "https://joaopessoa.ifpb.edu.br/horario/professor/796"
      }
    ],
    "location": [
      {
        "name": "SALA 04",
        "link": "https://joaopessoa.ifpb.edu.br/horario/sala/100"
      }
    ]
  },
  {
    "course": "EDIFICACOES SUBSEQUENTE",
    "semester": 3,
    "weekday": "segunda",
    "start": "20:50",
    "end": "21:40",
    "className": "MAT CON CIV II",
    "teacher": [
      {
        "name": "VAMBERTO",
        "link": "https://joaopessoa.ifpb.edu.br/horario/professor/410"
      }
    ],
    "location": [
      {
        "name": "LAB MAT.1",
        "link": "https://joaopessoa.ifpb.edu.br/horario/laboratorio/62"
      }
    ]
  },
  {
    "course": "EDIFICACOES SUBSEQUENTE",
    "semester": 3,
    "weekday": "terca",
    "start": "20:50",
    "end": "21:40",
    "className": "DES AUX COM II",
    "teacher": [
      {
        "name": "MANOEL BRITO",
        "link": "https://joaopessoa.ifpb.edu.br/horario/professor/266"
      }
    ],
    "location": [
      {
        "name": "SL INFO 31",
        "link": "https://joaopessoa.ifpb.edu.br/horario/sala/54"
      }
    ]
  },
  {
    "course": "EDIFICACOES SUBSEQUENTE",
    "semester": 3,
    "weekday": "quarta",
    "start": "20:50",
    "end": "21:40",
    "className": "TEC CONST A",
    "teacher": [
      {
        "name": "RENATA PAIVA",
        "link": "https://joaopessoa.ifpb.edu.br/horario/professor/9"
      }
    ],
    "location": [
      {
        "name": "SALA 39",
        "link": "https://joaopessoa.ifpb.edu.br/horario/sala/42"
      }
    ]
  },
  {
    "course": "EDIFICACOES SUBSEQUENTE",
    "semester": 3,
    "weekday": "quinta",
    "start": "20:50",
    "end": "21:40",
    "className": "MEC SOLOS",
    "teacher": [
      {
        "name": "EVANDRO",
        "link": "https://joaopessoa.ifpb.edu.br/horario/professor/126"
      }
    ],
    "location": [
      {
        "name": "LAB SOLOS",
        "link": "https://joaopessoa.ifpb.edu.br/horario/laboratorio/64"
      }
    ]
  },
  {
    "course": "EDIFICACOES SUBSEQUENTE",
    "semester": 3,
    "weekday": "sexta",
    "start": "20:50",
    "end": "21:40",
    "className": "TEC CONST A",
    "teacher": [
      {
        "name": "MELLYNE ",
        "link": "https://joaopessoa.ifpb.edu.br/horario/professor/796"
      }
    ],
    "location": [
      {
        "name": "SALA 04",
        "link": "https://joaopessoa.ifpb.edu.br/horario/sala/100"
      }
    ]
  },
  {
    "course": "EDIFICACOES SUBSEQUENTE",
    "semester": 3,
    "weekday": "quinta",
    "start": "21:40",
    "end": "22:30",
    "className": "TOPOGRAFIA",
    "teacher": [
      {
        "name": "MARCONI ANTAO",
        "link": "https://joaopessoa.ifpb.edu.br/horario/professor/283"
      }
    ],
    "location": []
  },
  {
    "course": "EDIFICACOES SUBSEQUENTE",
    "semester": 3,
    "weekday": "sexta",
    "start": "21:40",
    "end": "22:30",
    "className": "TOPOGRAFIA",
    "teacher": [
      {
        "name": "MARCONI ANTAO",
        "link": "https://joaopessoa.ifpb.edu.br/horario/professor/283"
      }
    ],
    "location": []
  },
  {
    "course": "EDIFICACOES SUBSEQUENTE",
    "semester": 4,
    "weekday": "segunda",
    "start": "18:20",
    "end": "19:10",
    "className": "PROJETO HIDROS",
    "teacher": [
      {
        "name": "GERALDO MOURA",
        "link": "https://joaopessoa.ifpb.edu.br/horario/professor/157"
      }
    ],
    "location": [
      {
        "name": "SL INFO 31",
        "link": "https://joaopessoa.ifpb.edu.br/horario/sala/54"
      }
    ]
  },
  {
    "course": "EDIFICACOES SUBSEQUENTE",
    "semester": 4,
    "weekday": "terca",
    "start": "18:20",
    "end": "19:10",
    "className": "PROJETO ELET",
    "teacher": [
      {
        "name": "CIRO",
        "link": "https://joaopessoa.ifpb.edu.br/horario/professor/74"
      }
    ],
    "location": [
      {
        "name": "SALA 39",
        "link": "https://joaopessoa.ifpb.edu.br/horario/sala/42"
      }
    ]
  },
  {
    "course": "EDIFICACOES SUBSEQUENTE",
    "semester": 4,
    "weekday": "quarta",
    "start": "18:20",
    "end": "19:10",
    "className": "DES ESTR",
    "teacher": [
      {
        "name": "ANA CLAUDIA",
        "link": "https://joaopessoa.ifpb.edu.br/horario/professor/27"
      }
    ],
    "location": [
      {
        "name": "ATELIER.1",
        "link": "https://joaopessoa.ifpb.edu.br/horario/laboratorio/83"
      }
    ]
  },
  {
    "course": "EDIFICACOES SUBSEQUENTE",
    "semester": 4,
    "weekday": "quinta",
    "start": "18:20",
    "end": "19:10",
    "className": "PROJ ARQUIT",
    "teacher": [
      {
        "name": "MANOEL BRITO",
        "link": "https://joaopessoa.ifpb.edu.br/horario/professor/266"
      }
    ],
    "location": [
      {
        "name": "ATELIER.1",
        "link": "https://joaopessoa.ifpb.edu.br/horario/laboratorio/83"
      }
    ]
  },
  {
    "course": "EDIFICACOES SUBSEQUENTE",
    "semester": 4,
    "weekday": "sexta",
    "start": "18:20",
    "end": "19:10",
    "className": "EMPREENDED",
    "teacher": [
      {
        "name": "DEISE SILVA",
        "link": "https://joaopessoa.ifpb.edu.br/horario/professor/807"
      }
    ],
    "location": [
      {
        "name": "SALA 03",
        "link": "https://joaopessoa.ifpb.edu.br/horario/sala/101"
      }
    ]
  },
  {
    "course": "EDIFICACOES SUBSEQUENTE",
    "semester": 4,
    "weekday": "segunda",
    "start": "19:10",
    "end": "20:00",
    "className": "PROJETO HIDROS",
    "teacher": [
      {
        "name": "GERALDO MOURA",
        "link": "https://joaopessoa.ifpb.edu.br/horario/professor/157"
      }
    ],
    "location": [
      {
        "name": "SL INFO 31",
        "link": "https://joaopessoa.ifpb.edu.br/horario/sala/54"
      }
    ]
  },
  {
    "course": "EDIFICACOES SUBSEQUENTE",
    "semester": 4,
    "weekday": "terca",
    "start": "19:10",
    "end": "20:00",
    "className": "PROJETO ELET",
    "teacher": [
      {
        "name": "CIRO",
        "link": "https://joaopessoa.ifpb.edu.br/horario/professor/74"
      }
    ],
    "location": [
      {
        "name": "SALA 39",
        "link": "https://joaopessoa.ifpb.edu.br/horario/sala/42"
      }
    ]
  },
  {
    "course": "EDIFICACOES SUBSEQUENTE",
    "semester": 4,
    "weekday": "quarta",
    "start": "19:10",
    "end": "20:00",
    "className": "DES ESTR",
    "teacher": [
      {
        "name": "ANA CLAUDIA",
        "link": "https://joaopessoa.ifpb.edu.br/horario/professor/27"
      }
    ],
    "location": [
      {
        "name": "ATELIER.1",
        "link": "https://joaopessoa.ifpb.edu.br/horario/laboratorio/83"
      }
    ]
  },
  {
    "course": "EDIFICACOES SUBSEQUENTE",
    "semester": 4,
    "weekday": "quinta",
    "start": "19:10",
    "end": "20:00",
    "className": "PROJ ARQUIT",
    "teacher": [
      {
        "name": "MANOEL BRITO",
        "link": "https://joaopessoa.ifpb.edu.br/horario/professor/266"
      }
    ],
    "location": [
      {
        "name": "ATELIER.1",
        "link": "https://joaopessoa.ifpb.edu.br/horario/laboratorio/83"
      }
    ]
  },
  {
    "course": "EDIFICACOES SUBSEQUENTE",
    "semester": 4,
    "weekday": "sexta",
    "start": "19:10",
    "end": "20:00",
    "className": "EMPREENDED",
    "teacher": [
      {
        "name": "DEISE SILVA",
        "link": "https://joaopessoa.ifpb.edu.br/horario/professor/807"
      }
    ],
    "location": [
      {
        "name": "SALA 03",
        "link": "https://joaopessoa.ifpb.edu.br/horario/sala/101"
      }
    ]
  },
  {
    "course": "EDIFICACOES SUBSEQUENTE",
    "semester": 4,
    "weekday": "segunda",
    "start": "20:00",
    "end": "20:50",
    "className": "PROJETO HIDROS",
    "teacher": [
      {
        "name": "GERALDO MOURA",
        "link": "https://joaopessoa.ifpb.edu.br/horario/professor/157"
      }
    ],
    "location": [
      {
        "name": "SL INFO 31",
        "link": "https://joaopessoa.ifpb.edu.br/horario/sala/54"
      }
    ]
  },
  {
    "course": "EDIFICACOES SUBSEQUENTE",
    "semester": 4,
    "weekday": "terca",
    "start": "20:00",
    "end": "20:50",
    "className": "PROJETO ELET",
    "teacher": [
      {
        "name": "CIRO",
        "link": "https://joaopessoa.ifpb.edu.br/horario/professor/74"
      }
    ],
    "location": [
      {
        "name": "SALA 39",
        "link": "https://joaopessoa.ifpb.edu.br/horario/sala/42"
      }
    ]
  },
  {
    "course": "EDIFICACOES SUBSEQUENTE",
    "semester": 4,
    "weekday": "quarta",
    "start": "20:00",
    "end": "20:50",
    "className": "ADM PAN LEG OB",
    "teacher": [
      {
        "name": "CICERO SANTOS",
        "link": "https://joaopessoa.ifpb.edu.br/horario/professor/621"
      }
    ],
    "location": [
      {
        "name": "ATELIER.1",
        "link": "https://joaopessoa.ifpb.edu.br/horario/laboratorio/83"
      }
    ]
  },
  {
    "course": "EDIFICACOES SUBSEQUENTE",
    "semester": 4,
    "weekday": "quinta",
    "start": "20:00",
    "end": "20:50",
    "className": "PROJ ARQUIT",
    "teacher": [
      {
        "name": "MANOEL BRITO",
        "link": "https://joaopessoa.ifpb.edu.br/horario/professor/266"
      }
    ],
    "location": [
      {
        "name": "ATELIER.1",
        "link": "https://joaopessoa.ifpb.edu.br/horario/laboratorio/83"
      }
    ]
  },
  {
    "course": "EDIFICACOES SUBSEQUENTE",
    "semester": 4,
    "weekday": "segunda",
    "start": "20:50",
    "end": "21:40",
    "className": "PROJETO HIDROS",
    "teacher": [
      {
        "name": "GERALDO MOURA",
        "link": "https://joaopessoa.ifpb.edu.br/horario/professor/157"
      }
    ],
    "location": [
      {
        "name": "SL INFO 31",
        "link": "https://joaopessoa.ifpb.edu.br/horario/sala/54"
      }
    ]
  },
  {
    "course": "EDIFICACOES SUBSEQUENTE",
    "semester": 4,
    "weekday": "terca",
    "start": "20:50",
    "end": "21:40",
    "className": "PROJETO ELET",
    "teacher": [
      {
        "name": "CIRO",
        "link": "https://joaopessoa.ifpb.edu.br/horario/professor/74"
      }
    ],
    "location": [
      {
        "name": "SALA 39",
        "link": "https://joaopessoa.ifpb.edu.br/horario/sala/42"
      }
    ]
  },
  {
    "course": "EDIFICACOES SUBSEQUENTE",
    "semester": 4,
    "weekday": "quarta",
    "start": "20:50",
    "end": "21:40",
    "className": "ADM PAN LEG OB",
    "teacher": [
      {
        "name": "CICERO SANTOS",
        "link": "https://joaopessoa.ifpb.edu.br/horario/professor/621"
      }
    ],
    "location": [
      {
        "name": "ATELIER.1",
        "link": "https://joaopessoa.ifpb.edu.br/horario/laboratorio/83"
      }
    ]
  },
  {
    "course": "EDIFICACOES SUBSEQUENTE",
    "semester": 4,
    "weekday": "quinta",
    "start": "20:50",
    "end": "21:40",
    "className": "PROJ ARQUIT",
    "teacher": [
      {
        "name": "MANOEL BRITO",
        "link": "https://joaopessoa.ifpb.edu.br/horario/professor/266"
      }
    ],
    "location": [
      {
        "name": "ATELIER.1",
        "link": "https://joaopessoa.ifpb.edu.br/horario/laboratorio/83"
      }
    ]
  }
]